README.rst
setup.py
freesurfer_pp_moc/__init__.py
freesurfer_pp_moc/freesurfer_pp_moc.py
freesurfer_pp_moc.egg-info/PKG-INFO
freesurfer_pp_moc.egg-info/SOURCES.txt
freesurfer_pp_moc.egg-info/dependency_links.txt
freesurfer_pp_moc.egg-info/not-zip-safe
freesurfer_pp_moc.egg-info/requires.txt
freesurfer_pp_moc.egg-info/top_level.txt