Metadata-Version: 1.0
Name: freesurfer-pp-moc
Version: 2.2.0
Summary: A simple/dummy app that simulates a FreeSurfer run
Home-page: https://github.com/FNNDSC/pl-freesurfer_pp_moc
Author: Rudolph Pienaar
Author-email: rudolph.pienaar@gmail.com
License: MIT
Platform: UNKNOWN
